{
  "shows": [
    {
      "name": "Morning Glory",
      "day": "monday_tuesday_wednesday_thursday_friday",
      "hour": "EACH_SECOND BETWEEN_06:45:00_AND_11:00:00",
      "strategy": "stream",
      "on-error": "Offline Show",
      "sources": ["https://live.rockfm.ro:8443/rockfm.aacp"]
    },
    {
      "name": "Evening relax blues and french",
      "day": "monday_tuesday_wednesday_thursday_friday",
      "hour": "EACH_SECOND BETWEEN_11:00:00_AND_12:00:00",
      "strategy": "stream",
      "sources": [
        "https://str0.creacast.com/melody2",
        "https://i4.streams.ovh/sc/bluesrad/stream"
      ]
    },
    {
      "name": "Evening relax celtic",
      "day": "monday_tuesday_wednesday_thursday_friday",
      "hour": "EACH_SECOND BETWEEN_11:00:00_AND_12:00:00",
      "strategy": "stream",
      "sources": [
        "https://streaming.broadcastradio.com:11135/celtic",
        "http://192.111.140.11:8058/stream/1/"
      ]
    },
    {
      "name": "Evening relax 3 - alternative",
      "day": "monday_tuesday_wednesday_thursday_friday",
      "hour": "EACH_SECOND BETWEEN_12:00:00_AND_13:00:00",
      "strategy": "stream",
      "sources": [
        "https://ais-sa5.cdnstream1.com/b87537_128mp3",
        "https://streaming.exclusive.radio/er/00s/icecast.audio",
        "https://streaming.exclusive.radio/er/softrock/icecast.audio",
        "https://streaming.exclusive.radio/er/soul/icecast.audio"
      ]
    },
    {
      "name": "Select Pick 0",
      "day": "monday_tuesday_wednesday_thursday_friday",
      "hour": "EACH_SECOND BETWEEN_13:00:00_AND_14:00:00",
      "strategy": "stream",
      "sources": [
        "https://live.magicfm.ro/magicfm.aacp",
        "https://streaming.exclusive.radio/er/90s/icecast.audio",
        "https://streaming.exclusive.radio/er/indie/icecast.audio",
        "https://streaming.exclusive.radio/er/love80s/icecast.audio"
      ]
    },
    {
      "name": "SelectPick 1 (Swiss Jazz)",
      "day": "monday_tuesday_wednesday_thursday_friday",
      "hour": "EACH_SECOND BETWEEN_14:00:00_AND_15:00:00",
      "strategy": "stream",
      "sources": [
        "https://stream.srg-ssr.ch/m/rsj/mp3_128",
        "https://streaming.exclusive.radio/er/love50s/icecast.audio",
        "https://streaming.exclusive.radio/er/folk/icecast.audio",
        "https://streaming.exclusive.radio/er/lovemovies/icecast.audio"
      ]
    },
    {
      "name": "SelectPick 2",
      "day": "monday_tuesday_wednesday_thursday_friday",
      "hour": "EACH_SECOND BETWEEN_15:00:00_AND_16:00:00",
      "strategy": "stream",
      "sources": [
        "https://streaming.exclusive.radio/er/1920/icecast.audio",
        "https://streaming.exclusive.radio/er/1930/icecast.audio",
        "https://streaming.exclusive.radio/er/1940/icecast.audio",
        "https://streaming.exclusive.radio/er/50s/icecast.audio",
        "https://streaming.exclusive.radio/er/60s/icecast.audio",
        "https://streaming.exclusive.radio/er/blues/icecast.audio"
      ]
    },
    {
      "name": "SelectPick 3",
      "day": "monday_tuesday_wednesday_thursday_friday",
      "hour": "EACH_SECOND BETWEEN_16:00:00_AND_17:00:00",
      "strategy": "stream",
      "sources": [
        "https://stream.srg-ssr.ch/m/rsj/mp3_128",
        "https://streaming.exclusive.radio/er/love50s/icecast.audio",
        "https://streaming.exclusive.radio/er/70s/icecast.audio",
        "https://streaming.exclusive.radio/er/80s/icecast.audio",
        "https://streaming.exclusive.radio/er/blues/icecast.audio"
      ]
    },
    {
      "name": "Play local again",
      "day": "monday_tuesday_wednesday_thursday_friday",
      "hour": "EACH_SECOND BETWEEN_17:10:00_AND_18:00:00",
      "strategy": "sound-over-music",
      "sources": ["{RADIO_ROOT}sounds", "{RADIO_ROOT}muzica"]
    },
    {
      "name": "Exclusive night 1",
      "day": "monday_tuesday_wednesday_thursday_friday",
      "hour": "EACH_SECOND BETWEEN_18:00:00_AND_19:00:00",
      "strategy": "stream",
      "sources": [
        "https://streaming.exclusive.radio/er/davidbowie/icecast.audio",
        "https://streaming.exclusive.radio/er/rollingstones/icecast.audio",
        "https://streaming.exclusive.radio/er/beatles/icecast.audio"
      ]
    },
    {
      "name": "Exclusive night 2",
      "day": "monday_tuesday_wednesday_thursday_friday",
      "hour": "EACH_SECOND BETWEEN_19:00:00_AND_20:00:00",
      "strategy": "stream",
      "sources": [
        "https://streaming.exclusive.radio/er/davidbowie/icecast.audio",
        "https://streaming.exclusive.radio/er/rollingstones/icecast.audio",
        "https://streaming.exclusive.radio/er/beatles/icecast.audio"
      ]
    },
    {
      "name": "Exclusive night 3",
      "day": "monday_tuesday_wednesday_thursday_friday",
      "hour": "EACH_SECOND BETWEEN_20:00:00_AND_21:00:00",
      "strategy": "stream",
      "sources": [
        "https://streaming.exclusive.radio/er/davidbowie/icecast.audio",
        "https://streaming.exclusive.radio/er/rollingstones/icecast.audio",
        "https://streaming.exclusive.radio/er/beatles/icecast.audio"
      ]
    },
    {
      "name": "Exclusive night 3",
      "day": "monday_tuesday_wednesday_thursday_friday",
      "hour": "EACH_SECOND BETWEEN_21:00:00_AND_22:00:00",
      "strategy": "stream",
      "sources": [
        "https://streaming.exclusive.radio/er/davidbowie/icecast.audio",
        "https://streaming.exclusive.radio/er/rollingstones/icecast.audio",
        "https://streaming.exclusive.radio/er/beatles/icecast.audio"
      ]
    },



    {
      "name": "Exclusive David Bowie",
      "day": "SUNDAY",
      "hour": "EACH_SECOND BETWEEN_10:00:00_AND_11:30:00",
      "strategy": "stream",
      "sources": ["https://streaming.exclusive.radio/er/davidbowie/icecast.audio"]
    },
    {
      "name": "Exclusive Bruce Springsteen",
      "day": "SUNDAY",
      "hour": "EACH_SECOND BETWEEN_11:30:00_AND_12:30:00",
      "strategy": "stream",
      "sources": ["https://streaming.exclusive.radio/er/springsteen/icecast.audio"]
    },
    {
      "name": "Exclusive Led Zeppelin or Doors",
      "day": "SUNDAY",
      "hour": "EACH_SECOND BETWEEN_12:30:00_AND_13:30:00",
      "strategy": "stream",
      "sources": [
        "https://streaming.exclusive.radio/er/ledzeppelin/icecast.audio",
        "https://streaming.exclusive.radio/er/doors/icecast.audio"
      ]
    },
    {
      "name": "Exclusive Bob Dylan",
      "day": "SUNDAY",
      "hour": "EACH_SECOND BETWEEN_13:30:00_AND_14:30:00",
      "strategy": "sound-over-stream",
      "sources": ["{RADIO_ROOT}sounds", "https://streaming.exclusive.radio/er/bobdylan/icecast.audio"]
    },
    {
      "name": "Exclusive Rolling Stones",
      "day": "SUNDAY",
      "hour": "EACH_SECOND BETWEEN_14:30:00_AND_15:30:00",
      "strategy": "stream",
      "sources": ["https://streaming.exclusive.radio/er/rollingstones/icecast.audio"]
    },
    {
      "name": "Magic Gold Hits",
      "day": "SUNDAY",
      "hour": "EACH_SECOND BETWEEN_15:30:00_AND_16:00:00",
      "strategy": "sound-over-stream",
      "sources": ["{RADIO_ROOT}sounds", "https://live.magicfm.ro/magic.gold.hits"]
    },
    {
      "name": "Exclusive Queen",
      "day": "SUNDAY",
      "hour": "EACH_SECOND BETWEEN_16:00:00_AND_17:00:00",
      "strategy": "stream",
      "sources": ["https://streaming.exclusive.radio/er/queen/icecast.audio"]
    },
    {
      "name": "Exclusive Pink Floyd",
      "day": "SUNDAY",
      "hour": "EACH_SECOND BETWEEN_17:00:00_AND_18:00:00",
      "strategy": "stream",
      "sources": ["https://streaming.exclusive.radio/er/pinkfloyd/icecast.audio"]
    },
    {
      "name": "Exclusive Rory Gallagher",
      "day": "SUNDAY",
      "hour": "EACH_SECOND BETWEEN_19:00:00_AND_20:00:00",
      "strategy": "sound-over-stream",
      "sources": ["{RADIO_ROOT}sounds","https://streaming.exclusive.radio/er/rorygallagher/icecast.audio"]
    },
    {
      "name": "Exclusive White Stripes",
      "day": "SUNDAY",
      "hour": "EACH_SECOND BETWEEN_20:00:00_AND_21:00:00",
      "strategy": "sound-over-stream",
      "sources": ["{RADIO_ROOT}sounds","https://streaming.exclusive.radio/er/whitestripes/icecast.audio"]
    },
    {
      "name": "Exclusive Thin Lizzy",
      "day": "SUNDAY",
      "hour": "EACH_SECOND BETWEEN_19:00:00_AND_20:00:00",
      "strategy": "stream",
      "sources": ["https://streaming.exclusive.radio/er/thinlizzy/icecast.audio"]
    },
    {
      "name": "Exclusive Rock",
      "day": "SUNDAY",
      "hour": "EACH_SECOND BETWEEN_20:00:00_AND_22:00:00",
      "strategy": "stream",
      "sources": ["https://streaming.exclusive.radio/er/rock/icecast.audio"]
    }





  ]
}